odoo/addons/edi_purchase_oca/README.rst
odoo/addons/edi_purchase_oca/__init__.py
odoo/addons/edi_purchase_oca/__manifest__.py
odoo/addons/edi_purchase_oca/components/__init__.py
odoo/addons/edi_purchase_oca/components/listeners.py
odoo/addons/edi_purchase_oca/data/edi_configuration.xml
odoo/addons/edi_purchase_oca/demo/edi_backend.xml
odoo/addons/edi_purchase_oca/demo/edi_configuration.xml
odoo/addons/edi_purchase_oca/demo/edi_exchange_type.xml
odoo/addons/edi_purchase_oca/i18n/edi_purchase_oca.pot
odoo/addons/edi_purchase_oca/i18n/es.po
odoo/addons/edi_purchase_oca/i18n/it.po
odoo/addons/edi_purchase_oca/models/__init__.py
odoo/addons/edi_purchase_oca/models/purchase_order.py
odoo/addons/edi_purchase_oca/models/res_partner.py
odoo/addons/edi_purchase_oca/readme/CONTRIBUTORS.rst
odoo/addons/edi_purchase_oca/readme/DESCRIPTION.rst
odoo/addons/edi_purchase_oca/static/description/icon.png
odoo/addons/edi_purchase_oca/static/description/index.html
odoo/addons/edi_purchase_oca/tests/__init__.py
odoo/addons/edi_purchase_oca/tests/test_edi_conf.py
odoo/addons/edi_purchase_oca/views/edi_exchange_record_views.xml
odoo/addons/edi_purchase_oca/views/purchase_order_views.xml
odoo/addons/edi_purchase_oca/views/res_partner_view.xml
odoo14_addon_edi_purchase_oca-14.0.1.1.0.dist-info/METADATA
odoo14_addon_edi_purchase_oca-14.0.1.1.0.dist-info/WHEEL
odoo14_addon_edi_purchase_oca-14.0.1.1.0.dist-info/top_level.txt
odoo14_addon_edi_purchase_oca-14.0.1.1.0.dist-info/RECORD
