Metadata-Version: 2.1
Name: odoo14-addon-edi_purchase_oca
Version: 14.0.1.1.0
Summary: Define EDI Configuration for Purchase Orders
Home-page: https://github.com/OCA/edi
Author: ForgeFlow, Camptocamp, Odoo Community Association (OCA)
Author-email: support@odoo-community.org
License: LGPL-3
Classifier: Programming Language :: Python
Classifier: Framework :: Odoo
Classifier: Framework :: Odoo :: 14.0
Classifier: License :: OSI Approved :: GNU Lesser General Public License v3 (LGPLv3)
Requires-Python: >=3.6
Requires-Dist: odoo14-addon-component-event
Requires-Dist: odoo14-addon-edi-oca
Requires-Dist: odoo<14.1dev,>=14.0a
